Metadata-Version: 2.1
Name: distributions-atul
Version: 0.1
Summary: Gaussian distributions
